tweet_parser/__init__.py
tweet_parser/deprecator.py
tweet_parser/lazy_property.py
tweet_parser/tweet.py
tweet_parser/tweet_checking.py
tweet_parser/tweet_keys.py
tweet_parser/tweet_parser_errors.py
tweet_parser/getter_methods/__init__.py
tweet_parser/getter_methods/gnip_fields.py
tweet_parser/getter_methods/tweet_counts.py
tweet_parser/getter_methods/tweet_date.py
tweet_parser/getter_methods/tweet_embeds.py
tweet_parser/getter_methods/tweet_entities.py
tweet_parser/getter_methods/tweet_generator.py
tweet_parser/getter_methods/tweet_geo.py
tweet_parser/getter_methods/tweet_links.py
tweet_parser/getter_methods/tweet_reply.py
tweet_parser/getter_methods/tweet_text.py
tweet_parser/getter_methods/tweet_user.py
tweet_parser-1.13.2.data/scripts/parse_tweets.py
tweet_parser-1.13.2.dist-info/LICENSE
tweet_parser-1.13.2.dist-info/METADATA
tweet_parser-1.13.2.dist-info/WHEEL
tweet_parser-1.13.2.dist-info/top_level.txt
tweet_parser-1.13.2.dist-info/RECORD
