Metadata-Version: 1.0
Name: tweet_parser
Version: 1.13.2
Summary: Tools for Tweet parsing
Home-page: https://github.com/twitterdev/tweet_parser
Author: Fiona Pigott, Jeff Kolb, Josh Montague, Aaron Gonzales
Author-email: fpigott@twitter.com
License: MIT
Platform: UNKNOWN
